{"type":"message_sent","oritin":"972558850336-1521193605@g.us","time":1525509296439,"message":{"id":{"fromMe":true,"remote":"972558850336-1521193605@g.us","id":"820C107DBD588CB4C6CC3C1809417475","_serialized":"true_972558850336-1521193605@g.us_820C107DBD588CB4C6CC3C1809417475"},"body":"סוף סוף, רותם","type":"chat","t":1525509289,"notifyName":"","from":"972558850336@c.us","to":"972558850336-1521193605@g.us","self":"in","ack":-1,"invis":false,"isNewMsg":false,"star":false,"recvFresh":true,"isForwarded":false}}